rgrow_flood.cp311-win_amd64.pyd
rgrow_flood-1.0.1.dist-info/METADATA
rgrow_flood-1.0.1.dist-info/WHEEL
rgrow_flood-1.0.1.dist-info/top_level.txt
rgrow_flood-1.0.1.dist-info/RECORD
