Metadata-Version: 2.1
Name: rgrow_flood
Version: 1.0.1
Summary: Python package for image object operations
Author: Lei Wang
Author-email: leiwang@lsu.edu
Classifier: Programming Language :: C++
Classifier: License :: OSI Approved :: MIT License
Classifier: Operating System :: OS Independent
Requires-Python: >=3.6
